amplifyy/__init__.py
amplifyy/augmentations.py
amplifyy/main.py
amplifyy-0.1.dist-info/METADATA
amplifyy-0.1.dist-info/WHEEL
amplifyy-0.1.dist-info/entry_points.txt
amplifyy-0.1.dist-info/top_level.txt
amplifyy-0.1.dist-info/RECORD
