Metadata-Version: 2.1
Name: amplifyy
Version: 0.1
Summary: Image Augmentation Tool
Author: Adarsh Kesharwani
Author-email: <akesherwani900@gamil.com>
Keywords: python,image augement,augmentation
Requires-Dist: numpy
Requires-Dist: opencv-python ==4.10.0.84
Requires-Dist: pillow ==10.4.0
